MANIFEST.in
setup.py
./__init__.py
./__openerp__.py
./controllers.py
./models.py
./test_models.py
./tests/__init__.py
./tests/test_cases.py
i18n/ar.po
i18n/base_import.pot
i18n/bs.po
i18n/cs.po
i18n/de.po
i18n/es.po
i18n/et.po
i18n/fr.po
i18n/hr.po
i18n/hu.po
i18n/it.po
i18n/mk.po
i18n/mn.po
i18n/nb.po
i18n/nl.po
i18n/pl.po
i18n/pt.po
i18n/pt_BR.po
i18n/ro.po
i18n/ru.po
i18n/sl.po
i18n/tr.po
i18n/zh_CN.po
openerp_base_import.egg-info/PKG-INFO
openerp_base_import.egg-info/SOURCES.txt
openerp_base_import.egg-info/dependency_links.txt
openerp_base_import.egg-info/requires.txt
openerp_base_import.egg-info/top_level.txt
security/ir.model.access.csv
static/csv/External_id_3rd_party_application_product_categories.csv
static/csv/External_id_3rd_party_application_products.csv
static/csv/Name_products.csv
static/csv/database_import_test.sql
static/csv/m2m_customers_tags.csv
static/csv/o2m_customers_contacts.csv
static/csv/o2m_purchase_order_lines.csv
static/csv/purchase.order_functional_error_line_cant_adpat.csv
static/lib/javascript-state-machine/index.html
static/lib/javascript-state-machine/state-machine.js
static/lib/select2/select2.js
static/lib/select2/select2.png
static/lib/select2/select2x2.png
static/lib/select2/spinner.gif
static/src/js/import.js
static/src/xml/import.xml
static/test/states.js